LICENSE
MANIFEST.in
README.md
setup.py
crypto_scripts/__init__.py
crypto_scripts/broadcast.py
crypto_scripts/convert_private_key.py
crypto_scripts/create_private_key.py
crypto_scripts/cryptosend.py
crypto_scripts/explorer.py
crypto_scripts/get_block_sizes.py
crypto_scripts/subscribe.py
crypto_scripts/view_private_key_addresses.py
cryptos/__init__.py
cryptos/blocks.py
cryptos/cashaddr.py
cryptos/composite.py
cryptos/constants.py
cryptos/deterministic.py
cryptos/english.txt
cryptos/keystore.py
cryptos/main.py
cryptos/mnemonic.py
cryptos/opcodes.py
cryptos/py3specials.py
cryptos/ripemd.py
cryptos/script_utils.py
cryptos/segwit_addr.py
cryptos/stealth.py
cryptos/transaction.py
cryptos/types.py
cryptos/utils.py
cryptos/wallet.py
cryptos/wallet_utils.py
cryptos/coins/__init__.py
cryptos/coins/base.py
cryptos/coins/bitcoin.py
cryptos/coins/bitcoin_cash.py
cryptos/coins/dash.py
cryptos/coins/dogecoin.py
cryptos/coins/litecoin.py
cryptos/coins_async/__init__.py
cryptos/coins_async/base.py
cryptos/coins_async/bitcoin.py
cryptos/coins_async/bitcoin_cash.py
cryptos/coins_async/dash.py
cryptos/coins_async/dogecoin.py
cryptos/coins_async/litecoin.py
cryptos/electrumx_client/__init__.py
cryptos/electrumx_client/client.py
cryptos/electrumx_client/types.py
cryptos/electrumx_client/servers/bitcoin.json
cryptos/electrumx_client/servers/bitcoin_cash.json
cryptos/electrumx_client/servers/bitcoin_cash_testnet.json
cryptos/electrumx_client/servers/bitcoin_testnet.json
cryptos/electrumx_client/servers/dash.json
cryptos/electrumx_client/servers/dash_testnet.json
cryptos/electrumx_client/servers/doge.json
cryptos/electrumx_client/servers/doge_testnet.json
cryptos/electrumx_client/servers/litecoin.json
cryptos/electrumx_client/servers/litecoin_testnet.json
cryptos/electrumx_client/servers/testing.json
cryptos/explorers/__init__.py
cryptos/explorers/base_insight.py
cryptos/explorers/bitpay.py
cryptos/explorers/blockchain.py
cryptos/explorers/blockcypher.py
cryptos/explorers/blockdozer.py
cryptos_witness.egg-info/PKG-INFO
cryptos_witness.egg-info/SOURCES.txt
cryptos_witness.egg-info/dependency_links.txt
cryptos_witness.egg-info/entry_points.txt
cryptos_witness.egg-info/requires.txt
cryptos_witness.egg-info/top_level.txt
