Metadata-Version: 2.1
Name: cryptos-witness
Version: 2.0.9
Summary: Python Crypto Coin Tools
Home-page: https://github.com/gberdyshev/pybitcointools
Author: gberdyshev
Author-email: bga20100@gmail.com
Classifier: Development Status :: 5 - Production/Stable
Classifier: Intended Audience :: Developers
Classifier: Intended Audience :: Education
Classifier: License :: OSI Approved :: MIT License
Classifier: Operating System :: OS Independent
Classifier: Programming Language :: Python
Classifier: Programming Language :: Python :: 3
Classifier: Topic :: Security :: Cryptography
License-File: LICENSE
